pyhashxx.pyd
pyhashxx-0.1.3.data/headers/pycompat.h
pyhashxx-0.1.3.data/headers/xxhash.h
pyhashxx-0.1.3.dist-info/DESCRIPTION.rst
pyhashxx-0.1.3.dist-info/METADATA
pyhashxx-0.1.3.dist-info/metadata.json
pyhashxx-0.1.3.dist-info/RECORD
pyhashxx-0.1.3.dist-info/top_level.txt
pyhashxx-0.1.3.dist-info/WHEEL
tests/test_hash_bytes.py
tests/test_oneshot.py
tests/__init__.py
