Metadata-Version: 2.0
Name: pyhashxx
Version: 0.1.3
Summary: Python wrapper for xxHash algorithm
Home-page: http://github.com/ewencp/pyhashxx
Author: Ewen Cheslack-Postava
Author-email: me@ewencp.org
License: BSD
Platform: any
